[
  {
    "name": "Houston Rockets",
    "sport": "nba",
    "dps": 155.31,
    "marketEV": 29.35,
    "t1_ev": 25.36,
    "t2_shock": 24.88,
    "t3_bayes": 21.47,
    "t4_bias": 24.95,
    "stdDev": 31.41,
    "sharpe": 0.808
  },
  {
    "name": "Philadelphia Phillies",
    "sport": "mlb",
    "dps": 140.31,
    "marketEV": 28.26,
    "t1_ev": 23.57,
    "t2_shock": 23.13,
    "t3_bayes": 20.11,
    "t4_bias": 23.18,
    "stdDev": 30.81,
    "sharpe": 0.765
  },
  {
    "name": "LA Lakers",
    "sport": "nba",
    "dps": 137.32,
    "marketEV": 27.34,
    "t1_ev": 22.26,
    "t2_shock": 21.89,
    "t3_bayes": 19.16,
    "t4_bias": 21.88,
    "stdDev": 30.3,
    "sharpe": 0.735
  },
  {
    "name": "Houston Astros",
    "sport": "mlb",
    "dps": 119.94,
    "marketEV": 25.23,
    "t1_ev": 18.79,
    "t2_shock": 18.51,
    "t3_bayes": 16.61,
    "t4_bias": 18.47,
    "stdDev": 28.68,
    "sharpe": 0.655
  },
  {
    "name": "New York Mets",
    "sport": "mlb",
    "dps": 116.35,
    "marketEV": 24.69,
    "t1_ev": 17.99,
    "t2_shock": 17.73,
    "t3_bayes": 16.04,
    "t4_bias": 17.67,
    "stdDev": 28.3,
    "sharpe": 0.636
  },
  {
    "name": "Atlanta Braves",
    "sport": "mlb",
    "dps": 116.29,
    "marketEV": 24.69,
    "t1_ev": 17.97,
    "t2_shock": 17.72,
    "t3_bayes": 16.04,
    "t4_bias": 17.66,
    "stdDev": 28.26,
    "sharpe": 0.636
  },
  {
    "name": "Chicago Cubs",
    "sport": "mlb",
    "dps": 108.94,
    "marketEV": 24.21,
    "t1_ev": 17.11,
    "t2_shock": 16.86,
    "t3_bayes": 15.39,
    "t4_bias": 16.81,
    "stdDev": 27.76,
    "sharpe": 0.616
  },
  {
    "name": "Green Bay Packers",
    "sport": "nfl",
    "dps": 102.13,
    "marketEV": 31,
    "t1_ev": 27.43,
    "t2_shock": 26.81,
    "t3_bayes": 23.02,
    "t4_bias": 26.98,
    "stdDev": 32.02,
    "sharpe": 0.857
  },
  {
    "name": "Buffalo Bills",
    "sport": "nfl",
    "dps": 100.11,
    "marketEV": 30.51,
    "t1_ev": 26.7,
    "t2_shock": 26.18,
    "t3_bayes": 22.45,
    "t4_bias": 26.27,
    "stdDev": 31.78,
    "sharpe": 0.84
  },
  {
    "name": "Washington Capitals",
    "sport": "nhl",
    "dps": 99.19,
    "marketEV": 24.47,
    "t1_ev": 17.06,
    "t2_shock": 16.86,
    "t3_bayes": 15.37,
    "t4_bias": 16.75,
    "stdDev": 27.7,
    "sharpe": 0.616
  },
  {
    "name": "San Diego Padres",
    "sport": "mlb",
    "dps": 93.94,
    "marketEV": 22.72,
    "t1_ev": 14.46,
    "t2_shock": 14.3,
    "t3_bayes": 13.51,
    "t4_bias": 14.2,
    "stdDev": 26.12,
    "sharpe": 0.554
  },
  {
    "name": "Milwaukee Brewers",
    "sport": "mlb",
    "dps": 90.23,
    "marketEV": 22.72,
    "t1_ev": 14.42,
    "t2_shock": 14.22,
    "t3_bayes": 13.47,
    "t4_bias": 14.15,
    "stdDev": 26.1,
    "sharpe": 0.552
  },
  {
    "name": "New England Patriots",
    "sport": "nfl",
    "dps": 89.2,
    "marketEV": 28.11,
    "t1_ev": 23.21,
    "t2_shock": 22.77,
    "t3_bayes": 19.87,
    "t4_bias": 22.82,
    "stdDev": 30.69,
    "sharpe": 0.756
  },
  {
    "name": "Baltimore Orioles",
    "sport": "mlb",
    "dps": 89.04,
    "marketEV": 21.91,
    "t1_ev": 12.92,
    "t2_shock": 12.79,
    "t3_bayes": 12.41,
    "t4_bias": 12.68,
    "stdDev": 24.95,
    "sharpe": 0.518
  },
  {
    "name": "Golden State Warriors",
    "sport": "nba",
    "dps": 87.85,
    "marketEV": 20.93,
    "t1_ev": 11.02,
    "t2_shock": 10.88,
    "t3_bayes": 11.09,
    "t4_bias": 10.81,
    "stdDev": 23.47,
    "sharpe": 0.469
  },
  {
    "name": "Philadelphia Eagles",
    "sport": "nfl",
    "dps": 86.98,
    "marketEV": 27.6,
    "t1_ev": 22.28,
    "t2_shock": 21.93,
    "t3_bayes": 19.16,
    "t4_bias": 21.9,
    "stdDev": 30.27,
    "sharpe": 0.736
  },
  {
    "name": "Denver Broncos",
    "sport": "nfl",
    "dps": 86.88,
    "marketEV": 27.6,
    "t1_ev": 22.29,
    "t2_shock": 21.89,
    "t3_bayes": 19.16,
    "t4_bias": 21.91,
    "stdDev": 30.34,
    "sharpe": 0.735
  },
  {
    "name": "New Jersey Devils",
    "sport": "nhl",
    "dps": 86.85,
    "marketEV": 23.01,
    "t1_ev": 14.45,
    "t2_shock": 14.28,
    "t3_bayes": 13.5,
    "t4_bias": 14.19,
    "stdDev": 26.16,
    "sharpe": 0.552
  },
  {
    "name": "Orlando Magic",
    "sport": "nba",
    "dps": 84.07,
    "marketEV": 20.24,
    "t1_ev": 9.6,
    "t2_shock": 9.54,
    "t3_bayes": 10.1,
    "t4_bias": 9.42,
    "stdDev": 22.13,
    "sharpe": 0.434
  },
  {
    "name": "Houston Texans",
    "sport": "nfl",
    "dps": 82.44,
    "marketEV": 26.56,
    "t1_ev": 20.67,
    "t2_shock": 20.37,
    "t3_bayes": 17.98,
    "t4_bias": 20.32,
    "stdDev": 29.58,
    "sharpe": 0.699
  },
  {
    "name": "Detroit Tigers",
    "sport": "mlb",
    "dps": 82.02,
    "marketEV": 21.28,
    "t1_ev": 11.68,
    "t2_shock": 11.57,
    "t3_bayes": 11.54,
    "t4_bias": 11.46,
    "stdDev": 23.93,
    "sharpe": 0.488
  },
  {
    "name": "Texas Rangers",
    "sport": "mlb",
    "dps": 78.96,
    "marketEV": 20.24,
    "t1_ev": 9.56,
    "t2_shock": 9.49,
    "t3_bayes": 10.06,
    "t4_bias": 9.38,
    "stdDev": 22.05,
    "sharpe": 0.433
  },
  {
    "name": "Los Angeles Kings",
    "sport": "nhl",
    "dps": 77.04,
    "marketEV": 21.6,
    "t1_ev": 11.77,
    "t2_shock": 11.65,
    "t3_bayes": 11.63,
    "t4_bias": 11.56,
    "stdDev": 24.1,
    "sharpe": 0.489
  },
  {
    "name": "Kansas City Royals",
    "sport": "mlb",
    "dps": 75.84,
    "marketEV": 20.24,
    "t1_ev": 9.58,
    "t2_shock": 9.53,
    "t3_bayes": 10.08,
    "t4_bias": 9.4,
    "stdDev": 22.13,
    "sharpe": 0.433
  },
  {
    "name": "New York Rangers",
    "sport": "nhl",
    "dps": 75.12,
    "marketEV": 20.57,
    "t1_ev": 9.53,
    "t2_shock": 9.47,
    "t3_bayes": 10.04,
    "t4_bias": 9.36,
    "stdDev": 21.99,
    "sharpe": 0.434
  },
  {
    "name": "Atlanta Hawks",
    "sport": "nba",
    "dps": 74.07,
    "marketEV": 18.51,
    "t1_ev": 5.78,
    "t2_shock": 5.77,
    "t3_bayes": 7.46,
    "t4_bias": 5.67,
    "stdDev": 17.68,
    "sharpe": 0.327
  },
  {
    "name": "Miami Heat",
    "sport": "nba",
    "dps": 73.06,
    "marketEV": 18.33,
    "t1_ev": 5.43,
    "t2_shock": 5.43,
    "t3_bayes": 7.26,
    "t4_bias": 5.33,
    "stdDev": 17.16,
    "sharpe": 0.317
  },
  {
    "name": "Cleveland Guardians",
    "sport": "mlb",
    "dps": 72.96,
    "marketEV": 19.72,
    "t1_ev": 8.4,
    "t2_shock": 8.36,
    "t3_bayes": 9.25,
    "t4_bias": 8.25,
    "stdDev": 20.82,
    "sharpe": 0.404
  },
  {
    "name": "Detroit Lions",
    "sport": "nfl",
    "dps": 72.86,
    "marketEV": 24.46,
    "t1_ev": 17.11,
    "t2_shock": 16.89,
    "t3_bayes": 15.41,
    "t4_bias": 16.81,
    "stdDev": 27.79,
    "sharpe": 0.616
  },
  {
    "name": "Cincinnati Reds",
    "sport": "mlb",
    "dps": 72.82,
    "marketEV": 19.72,
    "t1_ev": 8.46,
    "t2_shock": 8.41,
    "t3_bayes": 9.29,
    "t4_bias": 8.3,
    "stdDev": 20.94,
    "sharpe": 0.404
  },
  {
    "name": "Winnipeg Jets",
    "sport": "nhl",
    "dps": 72.75,
    "marketEV": 20.06,
    "t1_ev": 8.46,
    "t2_shock": 8.4,
    "t3_bayes": 9.31,
    "t4_bias": 8.3,
    "stdDev": 20.89,
    "sharpe": 0.405
  },
  {
    "name": "Ottawa Senators",
    "sport": "nhl",
    "dps": 72.29,
    "marketEV": 20.57,
    "t1_ev": 9.59,
    "t2_shock": 9.51,
    "t3_bayes": 10.09,
    "t4_bias": 9.4,
    "stdDev": 22.07,
    "sharpe": 0.434
  },
  {
    "name": "Arizona Diamondbacks",
    "sport": "mlb",
    "dps": 71.39,
    "marketEV": 18.99,
    "t1_ev": 6.92,
    "t2_shock": 6.89,
    "t3_bayes": 8.25,
    "t4_bias": 6.78,
    "stdDev": 19.21,
    "sharpe": 0.36
  },
  {
    "name": "Philadelphia 76ers",
    "sport": "nba",
    "dps": 71.39,
    "marketEV": 18.03,
    "t1_ev": 4.69,
    "t2_shock": 4.68,
    "t3_bayes": 6.71,
    "t4_bias": 4.6,
    "stdDev": 16.03,
    "sharpe": 0.293
  },
  {
    "name": "Los Angeles Chargers",
    "sport": "nfl",
    "dps": 71.31,
    "marketEV": 24.12,
    "t1_ev": 16.55,
    "t2_shock": 16.3,
    "t3_bayes": 15.01,
    "t4_bias": 16.25,
    "stdDev": 27.46,
    "sharpe": 0.603
  },
  {
    "name": "San Francisco 49ers",
    "sport": "nfl",
    "dps": 71.05,
    "marketEV": 24.06,
    "t1_ev": 16.27,
    "t2_shock": 16.08,
    "t3_bayes": 14.77,
    "t4_bias": 15.98,
    "stdDev": 27.24,
    "sharpe": 0.597
  },
  {
    "name": "Toronto Raptors",
    "sport": "nba",
    "dps": 68.73,
    "marketEV": 17.56,
    "t1_ev": 3.57,
    "t2_shock": 3.56,
    "t3_bayes": 5.95,
    "t4_bias": 3.5,
    "stdDev": 14.1,
    "sharpe": 0.253
  },
  {
    "name": "Montreal Canadiens",
    "sport": "nhl",
    "dps": 68.2,
    "marketEV": 19.67,
    "t1_ev": 7.66,
    "t2_shock": 7.59,
    "t3_bayes": 8.76,
    "t4_bias": 7.51,
    "stdDev": 20.06,
    "sharpe": 0.382
  },
  {
    "name": "Minnesota Wild",
    "sport": "nhl",
    "dps": 68.12,
    "marketEV": 19.67,
    "t1_ev": 7.58,
    "t2_shock": 7.51,
    "t3_bayes": 8.66,
    "t4_bias": 7.43,
    "stdDev": 19.94,
    "sharpe": 0.38
  },
  {
    "name": "San Francisco Giants",
    "sport": "mlb",
    "dps": 67.23,
    "marketEV": 18.73,
    "t1_ev": 6.3,
    "t2_shock": 6.26,
    "t3_bayes": 7.82,
    "t4_bias": 6.18,
    "stdDev": 18.38,
    "sharpe": 0.343
  },
  {
    "name": "Milwaukee Bucks",
    "sport": "nba",
    "dps": 66.03,
    "marketEV": 17.09,
    "t1_ev": 2.37,
    "t2_shock": 2.37,
    "t3_bayes": 5.12,
    "t4_bias": 2.32,
    "stdDev": 11.57,
    "sharpe": 0.204
  },
  {
    "name": "Anaheim Ducks",
    "sport": "nhl",
    "dps": 65.64,
    "marketEV": 19.09,
    "t1_ev": 6.32,
    "t2_shock": 6.28,
    "t3_bayes": 7.85,
    "t4_bias": 6.2,
    "stdDev": 18.42,
    "sharpe": 0.343
  },
  {
    "name": "LA Clippers",
    "sport": "nba",
    "dps": 64.65,
    "marketEV": 16.85,
    "t1_ev": 1.8,
    "t2_shock": 1.79,
    "t3_bayes": 4.77,
    "t4_bias": 1.76,
    "stdDev": 10.12,
    "sharpe": 0.178
  },
  {
    "name": "Baltimore Ravens",
    "sport": "nfl",
    "dps": 64.12,
    "marketEV": 23.94,
    "t1_ev": 16.12,
    "t2_shock": 15.91,
    "t3_bayes": 14.68,
    "t4_bias": 15.83,
    "stdDev": 27.19,
    "sharpe": 0.593
  },
  {
    "name": "Dallas Mavericks",
    "sport": "nba",
    "dps": 63.87,
    "marketEV": 16.71,
    "t1_ev": 1.48,
    "t2_shock": 1.47,
    "t3_bayes": 4.57,
    "t4_bias": 1.45,
    "stdDev": 9.22,
    "sharpe": 0.16
  },
  {
    "name": "Tampa Bay Rays",
    "sport": "mlb",
    "dps": 63.1,
    "marketEV": 18.03,
    "t1_ev": 4.71,
    "t2_shock": 4.7,
    "t3_bayes": 6.74,
    "t4_bias": 4.62,
    "stdDev": 16.05,
    "sharpe": 0.293
  },
  {
    "name": "Jacksonville Jaguars",
    "sport": "nfl",
    "dps": 63.05,
    "marketEV": 23.66,
    "t1_ev": 15.69,
    "t2_shock": 15.56,
    "t3_bayes": 14.41,
    "t4_bias": 15.41,
    "stdDev": 26.97,
    "sharpe": 0.582
  },
  {
    "name": "Chicago Bulls",
    "sport": "nba",
    "dps": 62.67,
    "marketEV": 16.5,
    "t1_ev": 0.91,
    "t2_shock": 0.9,
    "t3_bayes": 4.18,
    "t4_bias": 0.89,
    "stdDev": 7.25,
    "sharpe": 0.126
  },
  {
    "name": "Phoenix Suns",
    "sport": "nba",
    "dps": 61.82,
    "marketEV": 16.35,
    "t1_ev": 0.52,
    "t2_shock": 0.51,
    "t3_bayes": 3.95,
    "t4_bias": 0.51,
    "stdDev": 5.46,
    "sharpe": 0.095
  },
  {
    "name": "Oakland Athletics",
    "sport": "mlb",
    "dps": 61.27,
    "marketEV": 17.72,
    "t1_ev": 3.97,
    "t2_shock": 3.96,
    "t3_bayes": 6.24,
    "t4_bias": 3.89,
    "stdDev": 14.83,
    "sharpe": 0.268
  },
  {
    "name": "Brooklyn Nets",
    "sport": "nba",
    "dps": 61.11,
    "marketEV": 16.23,
    "t1_ev": 0.38,
    "t2_shock": 0.38,
    "t3_bayes": 3.7,
    "t4_bias": 0.37,
    "stdDev": 4.72,
    "sharpe": 0.08
  },
  {
    "name": "Charlotte Hornets",
    "sport": "nba",
    "dps": 61.11,
    "marketEV": 16.23,
    "t1_ev": 0.38,
    "t2_shock": 0.38,
    "t3_bayes": 3.69,
    "t4_bias": 0.37,
    "stdDev": 4.76,
    "sharpe": 0.08
  },
  {
    "name": "Indiana Pacers",
    "sport": "nba",
    "dps": 61.11,
    "marketEV": 16.23,
    "t1_ev": 0.37,
    "t2_shock": 0.38,
    "t3_bayes": 3.68,
    "t4_bias": 0.37,
    "stdDev": 4.72,
    "sharpe": 0.079
  },
  {
    "name": "Memphis Grizzlies",
    "sport": "nba",
    "dps": 61.11,
    "marketEV": 16.23,
    "t1_ev": 0.35,
    "t2_shock": 0.36,
    "t3_bayes": 3.68,
    "t4_bias": 0.35,
    "stdDev": 4.52,
    "sharpe": 0.079
  },
  {
    "name": "New Orleans Pelicans",
    "sport": "nba",
    "dps": 61.11,
    "marketEV": 16.23,
    "t1_ev": 0.37,
    "t2_shock": 0.37,
    "t3_bayes": 3.67,
    "t4_bias": 0.36,
    "stdDev": 4.66,
    "sharpe": 0.08
  },
  {
    "name": "Sacramento Kings",
    "sport": "nba",
    "dps": 61.11,
    "marketEV": 16.23,
    "t1_ev": 0.38,
    "t2_shock": 0.38,
    "t3_bayes": 3.72,
    "t4_bias": 0.37,
    "stdDev": 4.74,
    "sharpe": 0.08
  },
  {
    "name": "Utah Jazz",
    "sport": "nba",
    "dps": 61.11,
    "marketEV": 16.23,
    "t1_ev": 0.39,
    "t2_shock": 0.38,
    "t3_bayes": 3.69,
    "t4_bias": 0.38,
    "stdDev": 4.82,
    "sharpe": 0.081
  },
  {
    "name": "Washington Wizards",
    "sport": "nba",
    "dps": 61.11,
    "marketEV": 16.23,
    "t1_ev": 0.37,
    "t2_shock": 0.37,
    "t3_bayes": 3.71,
    "t4_bias": 0.36,
    "stdDev": 4.62,
    "sharpe": 0.08
  },
  {
    "name": "Pittsburgh Pirates",
    "sport": "mlb",
    "dps": 60.51,
    "marketEV": 17.56,
    "t1_ev": 3.56,
    "t2_shock": 3.55,
    "t3_bayes": 5.95,
    "t4_bias": 3.49,
    "stdDev": 14.12,
    "sharpe": 0.252
  },
  {
    "name": "Minnesota Twins",
    "sport": "mlb",
    "dps": 60.3,
    "marketEV": 17.56,
    "t1_ev": 3.61,
    "t2_shock": 3.61,
    "t3_bayes": 6.02,
    "t4_bias": 3.54,
    "stdDev": 14.22,
    "sharpe": 0.254
  },
  {
    "name": "St. Louis Blues",
    "sport": "nhl",
    "dps": 60.3,
    "marketEV": 17.94,
    "t1_ev": 3.58,
    "t2_shock": 3.58,
    "t3_bayes": 5.96,
    "t4_bias": 3.51,
    "stdDev": 14.14,
    "sharpe": 0.253
  },
  {
    "name": "New York Islanders",
    "sport": "nhl",
    "dps": 60.23,
    "marketEV": 17.94,
    "t1_ev": 3.6,
    "t2_shock": 3.59,
    "t3_bayes": 5.99,
    "t4_bias": 3.53,
    "stdDev": 14.21,
    "sharpe": 0.253
  },
  {
    "name": "Kansas City Chiefs",
    "sport": "nfl",
    "dps": 59.73,
    "marketEV": 22.81,
    "t1_ev": 14.12,
    "t2_shock": 13.95,
    "t3_bayes": 13.27,
    "t4_bias": 13.86,
    "stdDev": 25.88,
    "sharpe": 0.545
  },
  {
    "name": "Vancouver Canucks",
    "sport": "nhl",
    "dps": 59.45,
    "marketEV": 17.25,
    "t1_ev": 1.79,
    "t2_shock": 1.79,
    "t3_bayes": 4.74,
    "t4_bias": 1.75,
    "stdDev": 10.02,
    "sharpe": 0.178
  },
  {
    "name": "Pittsburgh Penguins",
    "sport": "nhl",
    "dps": 58.19,
    "marketEV": 17.48,
    "t1_ev": 2.39,
    "t2_shock": 2.39,
    "t3_bayes": 5.18,
    "t4_bias": 2.34,
    "stdDev": 11.58,
    "sharpe": 0.206
  },
  {
    "name": "Boston Bruins",
    "sport": "nhl",
    "dps": 58.12,
    "marketEV": 17.48,
    "t1_ev": 2.38,
    "t2_shock": 2.39,
    "t3_bayes": 5.15,
    "t4_bias": 2.34,
    "stdDev": 11.6,
    "sharpe": 0.205
  },
  {
    "name": "Buffalo Sabres",
    "sport": "nhl",
    "dps": 58.12,
    "marketEV": 17.48,
    "t1_ev": 2.42,
    "t2_shock": 2.42,
    "t3_bayes": 5.19,
    "t4_bias": 2.37,
    "stdDev": 11.68,
    "sharpe": 0.207
  },
  {
    "name": "Philadelphia Flyers",
    "sport": "nhl",
    "dps": 58.12,
    "marketEV": 17.48,
    "t1_ev": 2.4,
    "t2_shock": 2.39,
    "t3_bayes": 5.18,
    "t4_bias": 2.35,
    "stdDev": 11.67,
    "sharpe": 0.206
  },
  {
    "name": "Seattle Kraken",
    "sport": "nhl",
    "dps": 57.07,
    "marketEV": 17.25,
    "t1_ev": 1.82,
    "t2_shock": 1.82,
    "t3_bayes": 4.79,
    "t4_bias": 1.79,
    "stdDev": 10.2,
    "sharpe": 0.179
  },
  {
    "name": "St. Louis Cardinals",
    "sport": "mlb",
    "dps": 56.75,
    "marketEV": 16.93,
    "t1_ev": 2.01,
    "t2_shock": 2,
    "t3_bayes": 4.92,
    "t4_bias": 1.96,
    "stdDev": 10.63,
    "sharpe": 0.189
  },
  {
    "name": "Miami Marlins",
    "sport": "mlb",
    "dps": 56.64,
    "marketEV": 16.93,
    "t1_ev": 1.98,
    "t2_shock": 1.97,
    "t3_bayes": 4.88,
    "t4_bias": 1.94,
    "stdDev": 10.62,
    "sharpe": 0.187
  },
  {
    "name": "Calgary Flames",
    "sport": "nhl",
    "dps": 56.08,
    "marketEV": 17.02,
    "t1_ev": 1.24,
    "t2_shock": 1.23,
    "t3_bayes": 4.43,
    "t4_bias": 1.22,
    "stdDev": 8.46,
    "sharpe": 0.147
  },
  {
    "name": "Los Angeles Angels",
    "sport": "mlb",
    "dps": 55.53,
    "marketEV": 16.71,
    "t1_ev": 1.44,
    "t2_shock": 1.43,
    "t3_bayes": 4.49,
    "t4_bias": 1.41,
    "stdDev": 9.08,
    "sharpe": 0.158
  },
  {
    "name": "Chicago Blackhawks",
    "sport": "nhl",
    "dps": 55.51,
    "marketEV": 16.9,
    "t1_ev": 0.94,
    "t2_shock": 0.93,
    "t3_bayes": 4.2,
    "t4_bias": 0.92,
    "stdDev": 7.43,
    "sharpe": 0.126
  },
  {
    "name": "Nashville Predators",
    "sport": "nhl",
    "dps": 55.2,
    "marketEV": 16.84,
    "t1_ev": 0.74,
    "t2_shock": 0.74,
    "t3_bayes": 4.04,
    "t4_bias": 0.72,
    "stdDev": 6.55,
    "sharpe": 0.113
  },
  {
    "name": "San Jose Sharks",
    "sport": "nhl",
    "dps": 55.2,
    "marketEV": 16.84,
    "t1_ev": 0.75,
    "t2_shock": 0.75,
    "t3_bayes": 4.07,
    "t4_bias": 0.73,
    "stdDev": 6.57,
    "sharpe": 0.114
  },
  {
    "name": "Chicago White Sox",
    "sport": "mlb",
    "dps": 53.74,
    "marketEV": 16.43,
    "t1_ev": 0.73,
    "t2_shock": 0.72,
    "t3_bayes": 4.05,
    "t4_bias": 0.71,
    "stdDev": 6.46,
    "sharpe": 0.112
  },
  {
    "name": "Colorado Rockies",
    "sport": "mlb",
    "dps": 53.74,
    "marketEV": 16.43,
    "t1_ev": 0.73,
    "t2_shock": 0.74,
    "t3_bayes": 4.06,
    "t4_bias": 0.72,
    "stdDev": 6.53,
    "sharpe": 0.112
  },
  {
    "name": "Washington Nationals",
    "sport": "mlb",
    "dps": 53.74,
    "marketEV": 16.43,
    "t1_ev": 0.7,
    "t2_shock": 0.71,
    "t3_bayes": 4.03,
    "t4_bias": 0.69,
    "stdDev": 6.35,
    "sharpe": 0.111
  },
  {
    "name": "Chicago Bears",
    "sport": "nfl",
    "dps": 52.02,
    "marketEV": 20.93,
    "t1_ev": 10.32,
    "t2_shock": 10.22,
    "t3_bayes": 10.6,
    "t4_bias": 10.13,
    "stdDev": 22.81,
    "sharpe": 0.452
  },
  {
    "name": "Tampa Bay Buccaneers",
    "sport": "nfl",
    "dps": 46.35,
    "marketEV": 19.57,
    "t1_ev": 7.49,
    "t2_shock": 7.44,
    "t3_bayes": 8.66,
    "t4_bias": 7.34,
    "stdDev": 19.87,
    "sharpe": 0.377
  },
  {
    "name": "Dallas Cowboys",
    "sport": "nfl",
    "dps": 45.29,
    "marketEV": 19.29,
    "t1_ev": 6.76,
    "t2_shock": 6.7,
    "t3_bayes": 8.12,
    "t4_bias": 6.63,
    "stdDev": 18.93,
    "sharpe": 0.357
  },
  {
    "name": "Cincinnati Bengals",
    "sport": "nfl",
    "dps": 45.17,
    "marketEV": 19.29,
    "t1_ev": 6.83,
    "t2_shock": 6.79,
    "t3_bayes": 8.21,
    "t4_bias": 6.7,
    "stdDev": 19.01,
    "sharpe": 0.359
  },
  {
    "name": "Pittsburgh Steelers",
    "sport": "nfl",
    "dps": 42.19,
    "marketEV": 18.55,
    "t1_ev": 4.98,
    "t2_shock": 4.97,
    "t3_bayes": 6.88,
    "t4_bias": 4.89,
    "stdDev": 16.47,
    "sharpe": 0.303
  },
  {
    "name": "Indianapolis Colts",
    "sport": "nfl",
    "dps": 41.45,
    "marketEV": 18.37,
    "t1_ev": 4.67,
    "t2_shock": 4.63,
    "t3_bayes": 6.73,
    "t4_bias": 4.58,
    "stdDev": 16.02,
    "sharpe": 0.291
  },
  {
    "name": "New York Giants",
    "sport": "nfl",
    "dps": 40.99,
    "marketEV": 18.25,
    "t1_ev": 4.34,
    "t2_shock": 4.32,
    "t3_bayes": 6.49,
    "t4_bias": 4.25,
    "stdDev": 15.44,
    "sharpe": 0.281
  },
  {
    "name": "Washington Commanders",
    "sport": "nfl",
    "dps": 39.97,
    "marketEV": 18,
    "t1_ev": 3.68,
    "t2_shock": 3.65,
    "t3_bayes": 6.01,
    "t4_bias": 3.61,
    "stdDev": 14.32,
    "sharpe": 0.257
  },
  {
    "name": "Minnesota Vikings",
    "sport": "nfl",
    "dps": 39.93,
    "marketEV": 18,
    "t1_ev": 3.67,
    "t2_shock": 3.66,
    "t3_bayes": 6,
    "t4_bias": 3.6,
    "stdDev": 14.31,
    "sharpe": 0.257
  },
  {
    "name": "New Orleans Saints",
    "sport": "nfl",
    "dps": 39.12,
    "marketEV": 17.8,
    "t1_ev": 3.18,
    "t2_shock": 3.17,
    "t3_bayes": 5.69,
    "t4_bias": 3.12,
    "stdDev": 13.31,
    "sharpe": 0.239
  },
  {
    "name": "Atlanta Falcons",
    "sport": "nfl",
    "dps": 39,
    "marketEV": 17.77,
    "t1_ev": 3.13,
    "t2_shock": 3.13,
    "t3_bayes": 5.68,
    "t4_bias": 3.08,
    "stdDev": 13.22,
    "sharpe": 0.237
  },
  {
    "name": "Tennessee Titans",
    "sport": "nfl",
    "dps": 38.96,
    "marketEV": 17.74,
    "t1_ev": 3.03,
    "t2_shock": 3.01,
    "t3_bayes": 5.57,
    "t4_bias": 2.97,
    "stdDev": 13.08,
    "sharpe": 0.232
  },
  {
    "name": "Carolina Panthers",
    "sport": "nfl",
    "dps": 37.86,
    "marketEV": 17.46,
    "t1_ev": 2.4,
    "t2_shock": 2.39,
    "t3_bayes": 5.21,
    "t4_bias": 2.36,
    "stdDev": 11.73,
    "sharpe": 0.205
  },
  {
    "name": "Las Vegas Raiders",
    "sport": "nfl",
    "dps": 37.82,
    "marketEV": 17.48,
    "t1_ev": 2.42,
    "t2_shock": 2.42,
    "t3_bayes": 5.19,
    "t4_bias": 2.37,
    "stdDev": 11.74,
    "sharpe": 0.206
  },
  {
    "name": "Arizona Cardinals",
    "sport": "nfl",
    "dps": 36.64,
    "marketEV": 17.18,
    "t1_ev": 1.65,
    "t2_shock": 1.64,
    "t3_bayes": 4.68,
    "t4_bias": 1.61,
    "stdDev": 9.72,
    "sharpe": 0.169
  },
  {
    "name": "Cleveland Browns",
    "sport": "nfl",
    "dps": 36.32,
    "marketEV": 17.09,
    "t1_ev": 1.38,
    "t2_shock": 1.38,
    "t3_bayes": 4.47,
    "t4_bias": 1.35,
    "stdDev": 8.88,
    "sharpe": 0.155
  },
  {
    "name": "New York Jets",
    "sport": "nfl",
    "dps": 35.82,
    "marketEV": 16.97,
    "t1_ev": 1.07,
    "t2_shock": 1.07,
    "t3_bayes": 4.26,
    "t4_bias": 1.05,
    "stdDev": 7.85,
    "sharpe": 0.137
  },
  {
    "name": "Miami Dolphins",
    "sport": "nfl",
    "dps": 35.45,
    "marketEV": 16.9,
    "t1_ev": 0.89,
    "t2_shock": 0.88,
    "t3_bayes": 4.12,
    "t4_bias": 0.87,
    "stdDev": 7.08,
    "sharpe": 0.125
  }
]